odoo/addons/l10n_it_fiscal_payment_term/README.rst
odoo/addons/l10n_it_fiscal_payment_term/__init__.py
odoo/addons/l10n_it_fiscal_payment_term/__manifest__.py
odoo/addons/l10n_it_fiscal_payment_term/data/fatturapa_data.xml
odoo/addons/l10n_it_fiscal_payment_term/i18n/it.po
odoo/addons/l10n_it_fiscal_payment_term/i18n/l10n_it_fiscal_payment_term.pot
odoo/addons/l10n_it_fiscal_payment_term/models/__init__.py
odoo/addons/l10n_it_fiscal_payment_term/models/account.py
odoo/addons/l10n_it_fiscal_payment_term/readme/CONFIGURE.md
odoo/addons/l10n_it_fiscal_payment_term/readme/CONTRIBUTORS.md
odoo/addons/l10n_it_fiscal_payment_term/readme/DESCRIPTION.md
odoo/addons/l10n_it_fiscal_payment_term/security/ir.model.access.csv
odoo/addons/l10n_it_fiscal_payment_term/static/description/icon.png
odoo/addons/l10n_it_fiscal_payment_term/static/description/index.html
odoo/addons/l10n_it_fiscal_payment_term/tests/__init__.py
odoo/addons/l10n_it_fiscal_payment_term/tests/test_fiscal_payment_term.py
odoo/addons/l10n_it_fiscal_payment_term/views/account_view.xml
odoo_addon_l10n_it_fiscal_payment_term-16.0.1.0.0.8.dist-info/METADATA
odoo_addon_l10n_it_fiscal_payment_term-16.0.1.0.0.8.dist-info/WHEEL
odoo_addon_l10n_it_fiscal_payment_term-16.0.1.0.0.8.dist-info/top_level.txt
odoo_addon_l10n_it_fiscal_payment_term-16.0.1.0.0.8.dist-info/RECORD
